{
  "sections": {
    "main": {
      "type": "main-page",
      "disabled": true,
      "settings": {
        "content_width": "80ch"
      }
    },
    "3db86d21-e949-4476-90e5-64fecffed43e": {
      "type": "image-with-text-overlay",
      "blocks": {
        "template--18272984301870__3db86d21-e949-4476-90e5-64fecffed43e-16866450405d17acc7-0": {
          "type": "subheading",
          "settings": {
            "text": ""
          }
        },
        "template--18272984301870__3db86d21-e949-4476-90e5-64fecffed43e-16866450405d17acc7-1": {
          "type": "heading",
          "settings": {
            "text": "Bottom Bracket Socket Tool",
            "heading_tag": "h1"
          }
        },
        "template--18272984301870__3db86d21-e949-4476-90e5-64fecffed43e-16866450405d17acc7-2": {
          "type": "richtext",
          "settings": {
            "content": ""
          }
        }
      },
      "block_order": [
        "template--18272984301870__3db86d21-e949-4476-90e5-64fecffed43e-16866450405d17acc7-0",
        "template--18272984301870__3db86d21-e949-4476-90e5-64fecffed43e-16866450405d17acc7-1",
        "template--18272984301870__3db86d21-e949-4476-90e5-64fecffed43e-16866450405d17acc7-2"
      ],
      "settings": {
        "full_width": true,
        "allow_transparent_header": false,
        "enable_parallax": false,
        "image_size": "md",
        "image": "shopify:\/\/shop_images\/dce7df15071e61f8adbb6302fbbe4575290db95c.png",
        "mobile_text_position": "place-self-center text-center",
        "desktop_text_position": "sm:place-self-center sm:text-center",
        "text_color": "#ffffff",
        "overlay_color": "#000000",
        "overlay_opacity": 30
      }
    },
    "d2fcbbb5-7f3b-4a7c-8e22-f4f5ad8a1f55": {
      "type": "rich-text",
      "blocks": {
        "template--19576491704622__d2fcbbb5-7f3b-4a7c-8e22-f4f5ad8a1f55-16868258995f6d968b-0": {
          "type": "subheading",
          "settings": {
            "text": ""
          }
        },
        "template--19576491704622__d2fcbbb5-7f3b-4a7c-8e22-f4f5ad8a1f55-16868258995f6d968b-1": {
          "type": "heading",
          "settings": {
            "text": "",
            "heading_tag": "h1",
            "text_color": "",
            "gradient": ""
          }
        },
        "template--19576491704622__d2fcbbb5-7f3b-4a7c-8e22-f4f5ad8a1f55-16868258995f6d968b-2": {
          "type": "richtext",
          "settings": {
            "content": "<p>The CeramicSpeed Bottom Bracket Dual Socket Tool has a magnetic center guide for 22.2, 24, 28 and 30mm bearing bore. There's a stable engagement with cups for easy installation and extraction. <\/p><p>The tool is precision machined for scratch-free use - developed and designed in Denmark. <\/p>"
          }
        },
        "db2bf278-4797-4cdb-b579-3f17ab407add": {
          "type": "image",
          "settings": {
            "image": "shopify:\/\/shop_images\/108708-09_some1.png",
            "width_mode": "custom",
            "max_width": 600,
            "mobile_max_width": 400
          }
        },
        "eec29d1a-1b85-459a-83f0-5c35a99c26e6": {
          "type": "button",
          "settings": {
            "style": "fill",
            "size": "base",
            "text": "BB Socket Tool Compatibility Overview",
            "url": "https:\/\/cdn.shopify.com\/s\/files\/1\/0726\/7542\/6606\/files\/tech-sheet_ceramicspeed-bb-socket-tool-compatibility_3.pdf?v=1686828967",
            "background": "",
            "text_color": ""
          }
        }
      },
      "block_order": [
        "template--19576491704622__d2fcbbb5-7f3b-4a7c-8e22-f4f5ad8a1f55-16868258995f6d968b-0",
        "template--19576491704622__d2fcbbb5-7f3b-4a7c-8e22-f4f5ad8a1f55-16868258995f6d968b-1",
        "template--19576491704622__d2fcbbb5-7f3b-4a7c-8e22-f4f5ad8a1f55-16868258995f6d968b-2",
        "db2bf278-4797-4cdb-b579-3f17ab407add",
        "eec29d1a-1b85-459a-83f0-5c35a99c26e6"
      ],
      "settings": {
        "full_width": true,
        "content_width": "small",
        "text_position": "center",
        "background": "",
        "background_gradient": "",
        "text_color": ""
      }
    },
    "838f8f8f-262d-47e4-ab4b-ad70d0b8887d": {
      "type": "media-with-text",
      "blocks": {
        "template--19576540201262__838f8f8f-262d-47e4-ab4b-ad70d0b8887d-168682905678cd62de-0": {
          "type": "image",
          "settings": {
            "image": "shopify:\/\/shop_images\/d8932cc899c19fd533c8b6ee82e0edf715e68c9d.png",
            "media_width": 50,
            "media_position": "start",
            "text_position": "place-self-center text-center",
            "icon": "none",
            "icon_width": 48,
            "subheading": "",
            "title": "CeramicSpeed Dual Socket Tool T45 Colnago\/T47",
            "content": "<p>Side A: 16 Notch ø52,2 for T47X86 for Shimano\/SRAM GXP\/Campagnolo UT\/30mm\/SRAM DUB. Side B: 16 Notch ø53 for T45 (Colnago Threadfit 82.5) Shimano\/SRAM GXP\/Campagnolo UT\/30mm\/SRAM DUB.<\/p>",
            "link_text": "Buy now",
            "link_url": "",
            "background": "rgba(0,0,0,0)",
            "background_gradient": "",
            "text_color": "#000000",
            "text_gradient": "",
            "button_background": "",
            "button_text_color": ""
          }
        },
        "40aad508-69ae-4cd7-906a-8ebff8d39f30": {
          "type": "image",
          "settings": {
            "image": "shopify:\/\/shop_images\/ces331-bb-tool-t45_t47-assembly_rev01.jpg",
            "media_width": 50,
            "media_position": "alternating",
            "text_position": "place-self-center text-center",
            "icon": "none",
            "icon_width": 48,
            "subheading": "",
            "title": "",
            "content": "",
            "link_text": "",
            "link_url": "",
            "background": "rgba(0,0,0,0)",
            "background_gradient": "",
            "text_color": "#ffffff",
            "text_gradient": "",
            "button_background": "",
            "button_text_color": ""
          }
        },
        "7d3c03d7-a031-47c5-a45c-156304b3f9ad": {
          "type": "image",
          "settings": {
            "image": "shopify:\/\/shop_images\/04fcb458d4f47c706afdab9964f655c223a57487.png",
            "media_width": 50,
            "media_position": "start",
            "text_position": "place-self-center text-center",
            "icon": "none",
            "icon_width": 48,
            "subheading": "",
            "title": "CeramicSpeed Dual Socket Tool BSA\/ITA",
            "content": "<p>Side A: 16 Notch ø44 for BSA\/ITA\/BB30\/T47X68 for Shimano\/SRAM GXP\/Campagnolo UT. Side B: 12 Notch ø46,5 for BSA\/ITA\/T47X68 for 30mm\/SRAM DUB, BB30 SRAM DUB.<\/p>",
            "link_text": "",
            "link_url": "",
            "background": "rgba(0,0,0,0)",
            "background_gradient": "",
            "text_color": "#000000",
            "text_gradient": "",
            "button_background": "",
            "button_text_color": ""
          }
        },
        "fd407dc4-fd65-4850-9d20-d8e2f9f4af56": {
          "type": "image",
          "settings": {
            "image": "shopify:\/\/shop_images\/ces0330-bb-tool-bbt-69_bbt-79-assembly_rev01_7.jpg",
            "media_width": 50,
            "media_position": "alternating",
            "text_position": "place-self-center text-center",
            "icon": "none",
            "icon_width": 48,
            "subheading": "",
            "title": "",
            "content": "",
            "link_text": "",
            "link_url": "",
            "background": "rgba(0,0,0,0)",
            "background_gradient": "",
            "text_color": "#ffffff",
            "text_gradient": "",
            "button_background": "",
            "button_text_color": ""
          }
        }
      },
      "block_order": [
        "template--19576540201262__838f8f8f-262d-47e4-ab4b-ad70d0b8887d-168682905678cd62de-0",
        "40aad508-69ae-4cd7-906a-8ebff8d39f30",
        "7d3c03d7-a031-47c5-a45c-156304b3f9ad",
        "fd407dc4-fd65-4850-9d20-d8e2f9f4af56"
      ],
      "settings": {
        "full_width": false,
        "enable_parallax": true,
        "spacing": "small"
      }
    }
  },
  "order": [
    "main",
    "3db86d21-e949-4476-90e5-64fecffed43e",
    "d2fcbbb5-7f3b-4a7c-8e22-f4f5ad8a1f55",
    "838f8f8f-262d-47e4-ab4b-ad70d0b8887d"
  ]
}