{
  "sections": {
    "template-header": {
      "type": "template-header",
      "settings": {
        "full_width": true,
        "overlay_opacity": 30,
        "show_subcollections": true,
        "display_description": true,
        "bg_image": "shopify:\/\/shop_images\/Untitled_design_2.png"
      }
    },
    "multicolumn_RDbpA3": {
      "type": "multicolumn",
      "blocks": {
        "column_3TYLPY": {
          "type": "column",
          "settings": {
            "title": "Step 1",
            "heading_size": "h4",
            "text": "<p>Chose your design<\/p>",
            "link_label": "",
            "link": ""
          }
        },
        "column_6GQgTp": {
          "type": "column",
          "settings": {
            "title": "Step 2",
            "heading_size": "h4",
            "text": "<p>Drawings and price<\/p>",
            "link_label": "",
            "link": ""
          }
        },
        "column_zJU88b": {
          "type": "column",
          "settings": {
            "title": "Step 3",
            "heading_size": "h4",
            "text": "<p>Time for fittings<\/p>",
            "link_label": "",
            "link": ""
          }
        },
        "column_AGXtfd": {
          "type": "column",
          "settings": {
            "title": "Step 4",
            "heading_size": "h4",
            "text": "<p>Ready to order<\/p>",
            "link_label": "",
            "link": ""
          }
        },
        "column_3xjPBX": {
          "type": "column",
          "settings": {
            "title": "Step 5",
            "heading_size": "h4",
            "text": "<p>Delivery and payment<\/p>",
            "link_label": "",
            "link": ""
          }
        }
      },
      "block_order": [
        "column_3TYLPY",
        "column_6GQgTp",
        "column_zJU88b",
        "column_AGXtfd",
        "column_3xjPBX"
      ],
      "settings": {
        "heading": "5 step guide",
        "description": "<p>Our ordering proces is based 5 steps. Our customer service will be you all the way through from choosing design to delivery!<\/p>",
        "image_ratio": "circle",
        "columns_desktop": 5,
        "mobile_swipe": true,
        "text_alignment": "center",
        "disable_top_spacing": false,
        "disable_bottom_spacing": false
      }
    },
    "image_with_text_997E4J": {
      "type": "image-with-text",
      "blocks": {
        "subheading_zBTx9B": {
          "type": "subheading",
          "settings": {
            "text": ""
          }
        },
        "heading_gLEg9d": {
          "type": "heading",
          "settings": {
            "text": "1. Choose your design",
            "heading_size": "h3"
          }
        },
        "text_tQfXfm": {
          "type": "text",
          "settings": {
            "text": "<p>First you need to decide what kind of uniform you would like to have for your team. You can browse through or collections and make your design based on an existing design. You can also design your very own unique look and send some inspiration pictures to our sales consultant. <\/p><p>Please consider all the fabrics, colors, stones, and logos as well.  <\/p>"
          }
        }
      },
      "block_order": [
        "subheading_zBTx9B",
        "heading_gLEg9d",
        "text_tQfXfm"
      ],
      "settings": {
        "image": "shopify:\/\/shop_images\/Untitled_design_2_3ee89ca7-cf0f-440d-96c8-01caa5abff1b.png",
        "use_video": false,
        "video": "https:\/\/www.youtube.com\/watch?v=_9VUPq3SxOc",
        "video_autoplay": true,
        "height": "adapt",
        "desktop_image_width": "small",
        "layout": "image_first",
        "content_position": "text-left",
        "full_width": false,
        "color_bg": "#ffffff",
        "color_text": "#103a3a",
        "disable_top_spacing": true,
        "disable_bottom_spacing": true
      }
    },
    "image_with_text_FWiYjF": {
      "type": "image-with-text",
      "blocks": {
        "subheading_XpriFY": {
          "type": "subheading",
          "settings": {
            "text": ""
          }
        },
        "heading_XHeWDi": {
          "type": "heading",
          "settings": {
            "text": "2. Drawing & price ",
            "heading_size": "h3"
          }
        },
        "text_rWicGR": {
          "type": "text",
          "settings": {
            "text": "<p>After hearing your ideas, we will make you a drawing and give you an offer. <\/p><p>Please note that you get 3 rounds of drawings for free. <\/p>"
          }
        }
      },
      "block_order": [
        "subheading_XpriFY",
        "heading_XHeWDi",
        "text_rWicGR"
      ],
      "settings": {
        "image": "shopify:\/\/shop_images\/Untitled_design_4_ce2a0b2e-88ae-4eea-bc74-1dff1f17ead9.png",
        "use_video": false,
        "video": "https:\/\/www.youtube.com\/watch?v=_9VUPq3SxOc",
        "video_autoplay": true,
        "height": "adapt",
        "desktop_image_width": "small",
        "layout": "text_first",
        "content_position": "text-left",
        "full_width": false,
        "color_bg": "#ffffff",
        "color_text": "#103a3a",
        "disable_top_spacing": true,
        "disable_bottom_spacing": true
      }
    },
    "image_with_text_eLBj3n": {
      "type": "image-with-text",
      "blocks": {
        "subheading_NBpCwm": {
          "type": "subheading",
          "settings": {
            "text": ""
          }
        },
        "heading_Nrb8Wd": {
          "type": "heading",
          "settings": {
            "text": "3. Fittings",
            "heading_size": "h3"
          }
        },
        "text_CGwbaB": {
          "type": "text",
          "settings": {
            "text": "<p>When you have agreed on a design it is time for fittings. We will send you size sets so everyone at the team can find the right size. <\/p><p>Sizeset service includes all the sizes and shipping. The cost of service is 15 €. <\/p>"
          }
        }
      },
      "block_order": [
        "subheading_NBpCwm",
        "heading_Nrb8Wd",
        "text_CGwbaB"
      ],
      "settings": {
        "image": "shopify:\/\/shop_images\/Untitled_design_5_5edaa769-e137-453c-9a03-0e4ec7efe337.png",
        "use_video": false,
        "video": "https:\/\/www.youtube.com\/watch?v=_9VUPq3SxOc",
        "video_autoplay": true,
        "height": "adapt",
        "desktop_image_width": "small",
        "layout": "image_first",
        "content_position": "text-left",
        "full_width": false,
        "color_bg": "#ffffff",
        "color_text": "#103a3a",
        "disable_top_spacing": true,
        "disable_bottom_spacing": true
      }
    },
    "image_with_text_6nFDe3": {
      "type": "image-with-text",
      "blocks": {
        "subheading_cRphAj": {
          "type": "subheading",
          "settings": {
            "text": ""
          }
        },
        "heading_bcr9aU": {
          "type": "heading",
          "settings": {
            "text": "4. Ready to order",
            "heading_size": "h3"
          }
        },
        "text_ndjW6R": {
          "type": "text",
          "settings": {
            "text": "<p>When your drawing and price are comfirmed and fittings has been done, you are ready to order. You need to send back the size sets and your sales consultant will finalize your order. <\/p><p>You will receive order confirmation, which you need to check and approve within 2 days. If there is no response after 2 days, we will consider your order to be approved and move on to production. <\/p>"
          }
        }
      },
      "block_order": [
        "subheading_cRphAj",
        "heading_bcr9aU",
        "text_ndjW6R"
      ],
      "settings": {
        "image": "shopify:\/\/shop_images\/Untitled_design_6_94a46014-4670-4a0a-90ed-3bbeca0e0dd4.png",
        "use_video": false,
        "video": "https:\/\/www.youtube.com\/watch?v=_9VUPq3SxOc",
        "video_autoplay": true,
        "height": "adapt",
        "desktop_image_width": "small",
        "layout": "text_first",
        "content_position": "text-left",
        "full_width": false,
        "color_bg": "#ffffff",
        "color_text": "#103a3a",
        "disable_top_spacing": true,
        "disable_bottom_spacing": true
      }
    },
    "image_with_text_e4TFBE": {
      "type": "image-with-text",
      "blocks": {
        "subheading_WnygHH": {
          "type": "subheading",
          "settings": {
            "text": ""
          }
        },
        "heading_Tfe86V": {
          "type": "heading",
          "settings": {
            "text": "5. Delivery & payment ",
            "heading_size": "h3"
          }
        },
        "text_G94Ffi": {
          "type": "text",
          "settings": {
            "text": "<p>Delivery for your new dream uniforms is normally 11 weeks from the order. <\/p><p>For orders of EUR 3000 or more, 30% of the order amount is pre-invoiced for payment within 5 days. The rest of the order amount is invoiced with 8-day payment terms, calculated from the day of dispatch of your goods. <\/p><p>For orders under EUR 3000, the order amount is invoiced with an 8-day payment term, calculated from the day of dispatch of your goods. <\/p><p>PLEASE NOTE, in case of additional orders in a low quantity extra fee might be added to the prices.  <\/p>"
          }
        }
      },
      "block_order": [
        "subheading_WnygHH",
        "heading_Tfe86V",
        "text_G94Ffi"
      ],
      "settings": {
        "image": "shopify:\/\/shop_images\/Untitled_design_7_d1bf342e-3bf2-46d6-aa10-b7a3880363ff.png",
        "use_video": false,
        "video": "https:\/\/www.youtube.com\/watch?v=_9VUPq3SxOc",
        "video_autoplay": true,
        "height": "adapt",
        "desktop_image_width": "small",
        "layout": "image_first",
        "content_position": "text-left",
        "full_width": false,
        "color_bg": "#ffffff",
        "color_text": "#103a3a",
        "disable_top_spacing": true,
        "disable_bottom_spacing": true
      }
    },
    "main": {
      "type": "main-page",
      "settings": {}
    }
  },
  "order": [
    "template-header",
    "multicolumn_RDbpA3",
    "image_with_text_997E4J",
    "image_with_text_FWiYjF",
    "image_with_text_eLBj3n",
    "image_with_text_6nFDe3",
    "image_with_text_e4TFBE",
    "main"
  ]
}
