{
  "sections": {
    "main": {
      "type": "main-page",
      "disabled": true,
      "settings": {
        "content_width": "80ch"
      }
    },
    "3db86d21-e949-4476-90e5-64fecffed43e": {
      "type": "image-with-text-overlay",
      "blocks": {
        "template--18272984301870__3db86d21-e949-4476-90e5-64fecffed43e-16866450405d17acc7-0": {
          "type": "subheading",
          "settings": {
            "text": ""
          }
        },
        "template--18272984301870__3db86d21-e949-4476-90e5-64fecffed43e-16866450405d17acc7-1": {
          "type": "heading",
          "settings": {
            "text": "ISO 9001:2015",
            "heading_tag": "h1"
          }
        },
        "template--18272984301870__3db86d21-e949-4476-90e5-64fecffed43e-16866450405d17acc7-2": {
          "type": "richtext",
          "settings": {
            "content": ""
          }
        }
      },
      "block_order": [
        "template--18272984301870__3db86d21-e949-4476-90e5-64fecffed43e-16866450405d17acc7-0",
        "template--18272984301870__3db86d21-e949-4476-90e5-64fecffed43e-16866450405d17acc7-1",
        "template--18272984301870__3db86d21-e949-4476-90e5-64fecffed43e-16866450405d17acc7-2"
      ],
      "settings": {
        "full_width": true,
        "allow_transparent_header": false,
        "enable_parallax": false,
        "image_size": "md",
        "image": "shopify:\/\/shop_images\/a96dabef17a199c9d54c37f9dd15c1f23b78a6a9.png",
        "mobile_image": "shopify:\/\/shop_images\/a96dabef17a199c9d54c37f9dd15c1f23b78a6a9.png",
        "mobile_text_position": "place-self-center text-center",
        "desktop_text_position": "sm:place-self-center sm:text-center",
        "text_color": "#ffffff",
        "overlay_color": "#000000",
        "overlay_opacity": 30
      }
    },
    "54b777ff-0524-4dbf-81ae-b2db790351c5": {
      "type": "rich-text",
      "blocks": {
        "template--19542742008110__54b777ff-0524-4dbf-81ae-b2db790351c5-16866551449f2eefa7-0": {
          "type": "subheading",
          "settings": {
            "text": "CeramicSpeed certified after ISO 9001:2015"
          }
        },
        "template--19542742008110__54b777ff-0524-4dbf-81ae-b2db790351c5-16866551449f2eefa7-1": {
          "type": "heading",
          "settings": {
            "text": "",
            "heading_tag": "h1",
            "text_color": "",
            "gradient": ""
          }
        },
        "template--19542742008110__54b777ff-0524-4dbf-81ae-b2db790351c5-16866551449f2eefa7-2": {
          "type": "richtext",
          "settings": {
            "content": "<p>Quality has always been on our mind and we strive every day to supply what we promise, when we promise. This doesn’t change or improve with a certificate alone, but we strongly believe in ever increasing efficiency and with the ISO system implemented, we now have even more tools in the toolbox to support our aims.<br\/><br\/>The ISO 9001:2015 certification is internationally recognized as the world’s leading quality management standard and has been implemented by over one million organizations in over 170 countries globally.<br\/><br\/>The purpose of the standard is to assist companies in meeting statutory and regulatory requirements relating to their product while achieving excellence in their customer service and delivery.<br\/><\/p>"
          }
        },
        "a141581b-11cb-4579-994b-5df81bf40953": {
          "type": "button",
          "settings": {
            "style": "fill",
            "size": "xl",
            "text": "Download the certificate here",
            "url": "https:\/\/cdn.shopify.com\/s\/files\/1\/0726\/7542\/6606\/files\/iso-9001_2015-certificate.png",
            "background": "",
            "text_color": ""
          }
        },
        "56919ca0-36e2-4c1e-ab74-68e736d9a5e1": {
          "type": "image",
          "settings": {
            "image": "shopify:\/\/shop_images\/iso-9001_2015-certificate.png",
            "width_mode": "custom",
            "max_width": 600,
            "mobile_max_width": 400
          }
        }
      },
      "block_order": [
        "template--19542742008110__54b777ff-0524-4dbf-81ae-b2db790351c5-16866551449f2eefa7-0",
        "template--19542742008110__54b777ff-0524-4dbf-81ae-b2db790351c5-16866551449f2eefa7-1",
        "template--19542742008110__54b777ff-0524-4dbf-81ae-b2db790351c5-16866551449f2eefa7-2",
        "a141581b-11cb-4579-994b-5df81bf40953",
        "56919ca0-36e2-4c1e-ab74-68e736d9a5e1"
      ],
      "settings": {
        "full_width": true,
        "content_width": "small",
        "text_position": "center",
        "background": "",
        "background_gradient": "",
        "text_color": ""
      }
    }
  },
  "order": [
    "main",
    "3db86d21-e949-4476-90e5-64fecffed43e",
    "54b777ff-0524-4dbf-81ae-b2db790351c5"
  ]
}